{
    "tm_armory:armor/chain/front_chest": {
        "condition": {
            "type": "other_module",
            "condition": {
                "type": "tag",
                "tag": "elytra"
            }
        },
        "replace": {
            "display_name": "miapi:armored_elytra",
            "attributes": [
                {
                    "attribute": "minecraft:generic.armor",
                    "value": "([material.hardness] + 2 - ceil([material.flexibility]/4))/8*3",
                    "operation": "+",
                    "slot": "chest"
                },
                {
                    "attribute": "minecraft:generic.armor",
                    "value": "([material.hardness] + 1 - ceil([material.flexibility]/4)) / 8 * 3",
                    "operation": "+",
                    "slot": "chest"
                },
                {
                    "attribute": "minecraft:generic.armor_toughness",
                    "value": "((((([material.tier]-1-2)/(abs(([material.tier]-1)-2))))/(2))+0.5) * (([material.tier]-1)-1) / 3",
                    "operation": "+",
                    "slot": "chest"
                },
                {
                    "attribute": "minecraft:generic.knockback_resistance",
                    "value": "(((((([material.tier]-1)-3)/(abs(([material.tier]-1)-3))))/(2))+0.5) * (([material.tier]-1)-3) / 20",
                    "operation": "+",
                    "slot": "chest"
                }
            ]
        }
    }
}